MANIFEST.in
README.rst
requirements.txt
setup.py
queue_utils/__init__.py
queue_utils/endpoint.py
queue_utils/logger.py
queue_utils/worker.py
queue_utils.egg-info/PKG-INFO
queue_utils.egg-info/SOURCES.txt
queue_utils.egg-info/dependency_links.txt
queue_utils.egg-info/requires.txt
queue_utils.egg-info/top_level.txt