Metadata-Version: 1.0
Name: queue-utils
Version: 0.0.10
Summary: A set of utilities for tasks based on RabbitMQ
Home-page: https://github.com/zalando/queue_utils
Author: Zalando SE
Author-email: UNKNOWN
License: MIT
Platform: UNKNOWN
